jsonix/__init__.py
jsonix/jsonix.py
jsonix-0.3.dist-info/METADATA
jsonix-0.3.dist-info/WHEEL
jsonix-0.3.dist-info/top_level.txt
jsonix-0.3.dist-info/RECORD
