Metadata-Version: 2.4
Name: jsonix
Version: 0.3
Summary: Easy JSON manager with path-based access and edit support.
Author: Axmadjon Qaxxorov
Classifier: Programming Language :: Python :: 3
Classifier: License :: OSI Approved :: MIT License
Classifier: Operating System :: OS Independent
Requires-Python: >=3.6
Dynamic: author
Dynamic: classifier
Dynamic: description
Dynamic: description-content-type
Dynamic: requires-python
Dynamic: summary
